Realtime_Rendering_Tool/__init__.py
Realtime_Rendering_Tool/bundle.mjs
Realtime_Rendering_Tool/element.py
Realtime_Rendering_Tool/package.json
Realtime_Rendering_Tool/template.py
Realtime_Rendering_Tool-0.0.11.dist-info/LICENSE
Realtime_Rendering_Tool-0.0.11.dist-info/METADATA
Realtime_Rendering_Tool-0.0.11.dist-info/WHEEL
Realtime_Rendering_Tool-0.0.11.dist-info/entry_points.txt
Realtime_Rendering_Tool-0.0.11.dist-info/top_level.txt
Realtime_Rendering_Tool-0.0.11.dist-info/RECORD
