Metadata-Version: 2.1
Name: Realtime_Rendering_Tool
Version: 0.0.11
Summary: python-node.js package sample lib
Home-page: https://github.com/schooldevops/python-tutorials
Author: jhmun
Author-email: jhmun@miridih.com
Classifier: Programming Language :: Python :: 3
Classifier: License :: OSI Approved :: MIT License
Classifier: Operating System :: OS Independent
Requires-Python: >=3.6
License-File: LICENSE
